mizuhara/__init__.py
mizuhara/config_loader.py
mizuhara/core/__init__.py
mizuhara/core/routes.py
mizuhara/core/commands/__init__.py
mizuhara/core/commands/mizuhara.py
mizuhara/core/handlers/__init__.py
mizuhara/core/handlers/accounts.py
mizuhara/core/handlers/handlers.py
mizuhara/core/handlers/file/__init__.py
mizuhara/core/handlers/file/docs/__init__.py
mizuhara/core/handlers/file/docs/libre_office.py
mizuhara/core/handlers/file/docs/microsoft_office.py
mizuhara/core/handlers/file/multimedia/__init__.py
mizuhara/core/handlers/geo/__init__.py
mizuhara/translation/__init__.py
mizuhara/translation/buttons.yml
mizuhara/translation/exceptions.yml
mizuhara/translation/handlers.yml
mizuhara/translation/warnings.yml
mizuhara-0.0.56.dist-info/METADATA
mizuhara-0.0.56.dist-info/WHEEL
mizuhara-0.0.56.dist-info/entry_points.txt
mizuhara-0.0.56.dist-info/licenses/LICENSE
mizuhara-0.0.56.dist-info/RECORD
