Metadata-Version: 2.4
Name: mizuhara
Version: 0.0.56
Summary: Package Description
Author: luna-negra
License-Expression: MIT
License-File: LICENSE
Keywords: First,Python,Test,pypi
Classifier: Operating System :: OS Independent
Classifier: Programming Language :: Python :: 3
Requires-Dist: aiohttp>=3.11.11
Requires-Dist: coloredlogs>=15.0.1
Requires-Dist: pytelegrambotapi>=4.26.0
Requires-Dist: pyyaml>=6.0.2
Requires-Dist: requests>=2.32.3
